[
  {
    "personnel_number": 990896,
    "full_name": "مهدی لطفی پور",
    "department": "tech",
    "cooperation_start_date": "2022/05/22",
    "birthdate": "1991/12/23",
    "national_code": "0014170051",
    "phone": "09127171696",
    "first_name": "مهدی",
    "last_name": "لطفی پور",
    "email": "s.lotfi@jabama.com"
  },
  {
    "personnel_number": 95428,
    "full_name": "احمد ایزدپور",
    "department": "management",
    "cooperation_start_date": "2017/11/20",
    "birthdate": "1991/07/05",
    "national_code": 4670129740,
    "phone": "09391991004",
    "first_name": "احمد",
    "last_name": "ایزدپور",
    "email": "ahmad@jabama.com"
  },
  {
    "personnel_number": 97457,
    "full_name": "حسین مهدی خواه",
    "department": "strategy",
    "cooperation_start_date": "2019/07/23",
    "birthdate": "1990/07/29",
    "national_code": "0370313682",
    "phone": "09353314410",
    "first_name": "حسین",
    "last_name": "مهدی خواه",
    "email": "h.mahdikhah@jabama.com"
  },
  {
    "personnel_number": 97552,
    "full_name": "سعید حیدری",
    "department": "tech",
    "cooperation_start_date": "2019/10/12",
    "birthdate": "1986/12/12",
    "national_code": "0079406688",
    "phone": "09122894331",
    "first_name": "سعید",
    "last_name": "حیدری",
    "email": "s.heidari@jabama.com"
  },
  {
    "personnel_number": 1001024,
    "full_name": "گلرخ حمیدی",
    "department": "tech",
    "cooperation_start_date": "2024/12/21",
    "birthdate": "1995/04/21",
    "national_code": "0520805178",
    "phone": "09393399545",
    "first_name": "گلرخ",
    "last_name": "حمیدی",
    "email": "g.hamidi@jabama.com"
  },
  {
    "personnel_number": 1001025,
    "full_name": "احمد رحیمی زاده",
    "department": "tech",
    "cooperation_start_date": "2024/11/30",
    "birthdate": "2001/09/17",
    "national_code": "0024498671",
    "phone": "09033520921",
    "first_name": "احمد",
    "last_name": "رحیمی زاده",
    "email": "a.rahimizadeh@jabama.com"
  },
  {
    "personnel_number": 990233,
    "full_name": "یحیی بهمنی",
    "department": "tech",
    "cooperation_start_date": "2020/09/12",
    "birthdate": "1993/09/16",
    "national_code": "0016197178",
    "phone": "09353822992",
    "first_name": "یحیی",
    "last_name": "بهمنی",
    "email": "y.bahmani@jabama.com"
  },
  {
    "personnel_number": 990248,
    "full_name": "محمد زنگانه",
    "department": "experience",
    "cooperation_start_date": "2020/10/10",
    "birthdate": "1988/01/21",
    "national_code": 2269899547,
    "phone": "09114229399",
    "first_name": "محمد",
    "last_name": "زنگانه",
    "email": "m.zanganeh@jabama.com"
  },
  {
    "personnel_number": 991303,
    "full_name": "پارسا تیموری مقدم",
    "department": "operation",
    "cooperation_start_date": "2023/04/21",
    "birthdate": "1999/01/25",
    "national_code": "0021818231",
    "phone": "09120155650",
    "first_name": "پارسا",
    "last_name": "تیموری مقدم",
    "email": "p.teymoori@jabama.com"
  },
  {
    "personnel_number": 990320,
    "full_name": "پویا امیراحمدی",
    "department": "tech",
    "cooperation_start_date": "2020/12/05",
    "birthdate": "1992/02/21",
    "national_code": "0014969777",
    "phone": "09120208779",
    "first_name": "پویا",
    "last_name": "امیراحمدی",
    "email": "p.amirahmadi@jabama.com"
  },
  {
    "personnel_number": 990327,
    "full_name": "آرش صبوری",
    "department": "operation",
    "cooperation_start_date": "2020/11/24",
    "birthdate": "1998/02/26",
    "national_code": "0020892586",
    "phone": "09213214527",
    "first_name": "آرش",
    "last_name": "صبوری",
    "email": "a.saboori@jabama.com"
  },
  {
    "personnel_number": 991517,
    "full_name": "امیرحسین علی پور",
    "department": "operation",
    "cooperation_start_date": "2023/07/08",
    "birthdate": "2004/04/22",
    "national_code": "0150601484",
    "phone": "09195576378",
    "first_name": "امیرحسین",
    "last_name": "علی پور",
    "email": "am.alipour@jabama.com"
  },
  {
    "personnel_number": 990402,
    "full_name": "امین خدمتلو",
    "department": "product",
    "cooperation_start_date": "2021/05/22",
    "birthdate": "1992/06/16",
    "national_code": 5560099775,
    "phone": "09198087247",
    "first_name": "امین",
    "last_name": "خدمتلو",
    "email": "a.khedmatloo@jabama.com"
  },
  {
    "personnel_number": 1001005,
    "full_name": "داود حدادنظام",
    "department": "operation",
    "cooperation_start_date": "2024/10/12",
    "birthdate": "1996/12/24",
    "national_code": 1710263891,
    "phone": "09120451085",
    "first_name": "داود",
    "last_name": "حدادنظام",
    "email": "d.hadadnezam@jabama.com"
  },
  {
    "personnel_number": 991761,
    "full_name": "نسیم افروزی زاده",
    "department": "operation",
    "cooperation_start_date": "2024/01/22",
    "birthdate": "2001/01/24",
    "national_code": 1743364180,
    "phone": "09165389025",
    "first_name": "نسیم",
    "last_name": "افروزی زاده",
    "email": "n.afrouzizadeh@jabama.com"
  },
  {
    "personnel_number": 990549,
    "full_name": "فرنوش فراهانی",
    "department": "operation",
    "cooperation_start_date": "2022/04/21",
    "birthdate": "1994/08/08",
    "national_code": "0480614105",
    "phone": "09218736653",
    "first_name": "فرنوش",
    "last_name": "فراهانی",
    "email": "fa.farahani@jabama.com"
  },
  {
    "personnel_number": 991949,
    "full_name": "میلاد محمدی",
    "department": "marketing",
    "cooperation_start_date": "2024/06/01",
    "birthdate": "1995/12/26",
    "national_code": 3750388342,
    "phone": "09353914695",
    "first_name": "میلاد",
    "last_name": "محمدی",
    "email": "mil.mohammadi@jabama.com"
  },
  {
    "personnel_number": 990843,
    "full_name": "حمیدرضا حیدری",
    "department": "operation",
    "cooperation_start_date": "2022/01/15",
    "birthdate": "1995/07/03",
    "national_code": "0018211062",
    "phone": "09912230113",
    "first_name": "حمیدرضا",
    "last_name": "حیدری",
    "email": "ha.heydari@jabama.com"
  },
  {
    "personnel_number": 990844,
    "full_name": "علیرضا اکبری",
    "department": "marketing",
    "cooperation_start_date": "2022/01/05",
    "birthdate": "1992/10/26",
    "national_code": "0480465312",
    "phone": "09124234125",
    "first_name": "علیرضا",
    "last_name": "اکبری",
    "email": "a.akbari@jabama.com"
  },
  {
    "personnel_number": 990845,
    "full_name": "فرزانه بدرحداد",
    "department": "tech",
    "cooperation_start_date": "2022/01/10",
    "birthdate": "1991/07/06",
    "national_code": "0310550572",
    "phone": "09354101360",
    "first_name": "فرزانه",
    "last_name": "بدرحداد",
    "email": "f.hadad@jabama.com"
  },
  {
    "personnel_number": 991935,
    "full_name": "یاسمن پاکزاد",
    "department": "operation",
    "cooperation_start_date": "2024/03/20",
    "birthdate": "1996/12/26",
    "national_code": "0019716796",
    "phone": "09359419969",
    "first_name": "یاسمن",
    "last_name": "پاکزاد",
    "email": "y.pakzad@jabama.com"
  },
  {
    "personnel_number": 990936,
    "full_name": "نگار نظرعلیزاده",
    "department": "experience",
    "cooperation_start_date": "2022/03/21",
    "birthdate": "1988/07/09",
    "national_code": "0079808603",
    "phone": "09128179383",
    "first_name": "نگار",
    "last_name": "نظرعلیزاده",
    "email": "n.alizadeh@jabama.com"
  },
  {
    "personnel_number": 990966,
    "full_name": "رضا رجایی نژاد",
    "department": "operation",
    "cooperation_start_date": "2022/04/10",
    "birthdate": "1998/09/07",
    "national_code": 1742737269,
    "phone": "09928664423",
    "first_name": "رضا",
    "last_name": "رجایی نژاد",
    "email": "r.rajaei@jabama.com"
  },
  {
    "personnel_number": 991024,
    "full_name": "فاطمه عامری مقدم",
    "department": "operation",
    "cooperation_start_date": "2022/06/22",
    "birthdate": "1998/11/18",
    "national_code": "0480903387",
    "phone": "09368214016",
    "first_name": "فاطمه",
    "last_name": "عامری مقدم",
    "email": "f.ameri@jabama.com"
  },
  {
    "personnel_number": 991028,
    "full_name": "زهرا آبائی سنجانی",
    "department": "operation",
    "cooperation_start_date": "2022/06/22",
    "birthdate": "2000/11/08",
    "national_code": "0023649461",
    "phone": "09901909557",
    "first_name": "زهرا",
    "last_name": "آبائی سنجانی",
    "email": "z.abaee@jabama.com"
  },
  {
    "personnel_number": 991510,
    "full_name": "فرشاد امیری",
    "department": "operation",
    "cooperation_start_date": "2023/06/24",
    "birthdate": "1995/03/21",
    "national_code": 1341049407,
    "phone": "09056629637",
    "first_name": "فرشاد",
    "last_name": "امیری",
    "email": "f.amiri@jabama.com"
  },
  {
    "personnel_number": 991037,
    "full_name": "نیکو اسعدنیا",
    "department": "human resources",
    "cooperation_start_date": "2022/08/13",
    "birthdate": "1998/06/16",
    "national_code": "0311787002",
    "phone": "09905597285",
    "first_name": "نیکو",
    "last_name": "اسعدنیا",
    "email": "n.asadnia@jabama.com"
  },
  {
    "personnel_number": 991050,
    "full_name": "ناهید سالاری جوبنی",
    "department": "operation",
    "cooperation_start_date": "2022/09/28",
    "birthdate": "1993/07/05",
    "national_code": 2580596771,
    "phone": "09198952029",
    "first_name": "ناهید",
    "last_name": "سالاری جوبنی",
    "email": "e.salari@jabama.com"
  },
  {
    "personnel_number": 991054,
    "full_name": "مهسا مرادی میرمیرو",
    "department": "marketing",
    "cooperation_start_date": "2024/04/06",
    "birthdate": "1990/07/10",
    "national_code": "0310347920",
    "phone": "09126343745",
    "first_name": "مهسا",
    "last_name": "مرادی میرمیرو",
    "email": "ma.moradi@jabama.com"
  },
  {
    "personnel_number": 991056,
    "full_name": "حسین داستانی",
    "department": "strategy",
    "cooperation_start_date": "2022/11/22",
    "birthdate": "1996/10/08",
    "national_code": 1160313571,
    "phone": "09910416515",
    "first_name": "حسین",
    "last_name": "داستانی",
    "email": "h.dastani@jabama.com"
  },
  {
    "personnel_number": 991067,
    "full_name": "ماهرخ کاظمی",
    "department": "tech",
    "cooperation_start_date": "2023/06/22",
    "birthdate": "1994/12/13",
    "national_code": "0017764173",
    "phone": "09359640021",
    "first_name": "ماهرخ",
    "last_name": "کاظمی",
    "email": "ma.kazemi@jabama.com"
  },
  {
    "personnel_number": 991291,
    "full_name": "ابوالفضل انصاری",
    "department": "operation",
    "cooperation_start_date": "2023/01/21",
    "birthdate": "1991/12/09",
    "national_code": "0014159805",
    "phone": "09191210210",
    "first_name": "ابوالفضل",
    "last_name": "انصاری",
    "email": "a.ansari@jabama.com"
  },
  {
    "personnel_number": 991297,
    "full_name": "هادی پیشرفت",
    "department": "jaran",
    "cooperation_start_date": "2023/03/21",
    "birthdate": "1978/09/15",
    "national_code": "0059137819",
    "phone": "09126303449",
    "first_name": "هادی",
    "last_name": "پیشرفت",
    "email": "h.pishraft@alibaba.ir"
  },
  {
    "personnel_number": 991305,
    "full_name": "محمد امین اسمعیلی",
    "department": "product",
    "cooperation_start_date": "2023/06/22",
    "birthdate": "1998/10/01",
    "national_code": "0021449996",
    "phone": "09374054747",
    "first_name": "محمد",
    "last_name": "امین اسمعیلی",
    "email": "moh.esmaeili@jabama.com"
  },
  {
    "personnel_number": 991938,
    "full_name": "امین  محبی آشتیانی",
    "department": "tech",
    "cooperation_start_date": "2024/04/20",
    "birthdate": "1990/12/27",
    "national_code": "0012866229",
    "phone": "09127951910",
    "first_name": "امین",
    "last_name": " محبی آشتیانی",
    "email": "a.ashtiyani@jabama.com"
  },
  {
    "personnel_number": 991311,
    "full_name": "فاطمه نامدارپور",
    "department": "operation",
    "cooperation_start_date": "2023/04/21",
    "birthdate": "2000/08/01",
    "national_code": "0023399074",
    "phone": "09362761340",
    "first_name": "فاطمه",
    "last_name": "نامدارپور",
    "email": "r.namdarpour@jabama.com"
  },
  {
    "personnel_number": 991312,
    "full_name": "امیرحسین لاری",
    "department": "operation",
    "cooperation_start_date": "2023/04/21",
    "birthdate": "2001/08/18",
    "national_code": "0024525480",
    "phone": "09336889979",
    "first_name": "امیرحسین",
    "last_name": "لاری",
    "email": "a.lari@jabama.com"
  },
  {
    "personnel_number": 991830,
    "full_name": "حبیبه نعمت الله زاده",
    "department": "management",
    "cooperation_start_date": "2024/02/28",
    "birthdate": "1982/03/22",
    "national_code": 2991736585,
    "phone": "09365450030",
    "first_name": "حبیبه",
    "last_name": "نعمت الله زاده",
    "email": "a.nematolahzade@jabama.com"
  },
  {
    "personnel_number": 991940,
    "full_name": "سمانه جوادی",
    "department": "marketing",
    "cooperation_start_date": "2024/05/05",
    "birthdate": "1993/12/28",
    "national_code": "0016479319",
    "phone": "09369492223",
    "first_name": "سمانه",
    "last_name": "جوادی",
    "email": "s.javadi@jabama.com"
  },
  {
    "personnel_number": 991402,
    "full_name": "فاطمه عاشوری",
    "department": "operation",
    "cooperation_start_date": "2023/05/27",
    "birthdate": "1997/09/09",
    "national_code": "0020577095",
    "phone": "09125761951",
    "first_name": "فاطمه",
    "last_name": "عاشوری",
    "email": "g.ashoori@jabama.com"
  },
  {
    "personnel_number": 991974,
    "full_name": "همراز عرفاتی",
    "department": "tech",
    "cooperation_start_date": "2024/08/10",
    "birthdate": "2001/12/29",
    "national_code": "0441002358",
    "phone": "09339048121",
    "first_name": "همراز",
    "last_name": "عرفاتی",
    "email": "h.arafati@jabama.com"
  },
  {
    "personnel_number": 991428,
    "full_name": "آنیتا ملافیلابی",
    "department": "operation",
    "cooperation_start_date": "2023/06/10",
    "birthdate": "2001/07/03",
    "national_code": "0925746061",
    "phone": "09014326242",
    "first_name": "آنیتا",
    "last_name": "ملافیلابی",
    "email": "a.filabi@jabama.com"
  },
  {
    "personnel_number": 990764,
    "full_name": "امیرپارسا طایفه حاج حسینعلی تجریشی",
    "department": "operation",
    "cooperation_start_date": "2021/11/22",
    "birthdate": "2002/01/02",
    "national_code": "0150068220",
    "phone": "09395729816",
    "first_name": "امیرپارسا",
    "last_name": "طایفه حاج حسینعلی تجریشی",
    "email": "p.tajrishi@jabama.com"
  },
  {
    "personnel_number": 1001020,
    "full_name": "زهرا نجفی دهجلالی",
    "department": "operation",
    "cooperation_start_date": "2024/11/03",
    "birthdate": "1996/04/23",
    "national_code": 5560360066,
    "phone": "09352702088",
    "first_name": "زهرا",
    "last_name": "نجفی دهجلالی",
    "email": "z.najafi@jabama.com"
  },
  {
    "personnel_number": 991440,
    "full_name": "مجتبی رستگار",
    "department": "marketing",
    "cooperation_start_date": "2023/07/23",
    "birthdate": "1996/10/28",
    "national_code": "0019458071",
    "phone": "09129347024",
    "first_name": "مجتبی",
    "last_name": "رستگار",
    "email": "m.rastegar@jabama.com"
  },
  {
    "personnel_number": 991437,
    "full_name": "پگاه فدوی اردستانی",
    "department": "tech",
    "cooperation_start_date": "2023/07/08",
    "birthdate": "1991/03/28",
    "national_code": "0480298599",
    "phone": "09352258889",
    "first_name": "پگاه",
    "last_name": "فدوی اردستانی",
    "email": "p.fadavi@jabama.com"
  },
  {
    "personnel_number": 991512,
    "full_name": "مهدیه مقیسهء",
    "department": "tech",
    "cooperation_start_date": "2023/09/23",
    "birthdate": "2002/06/30",
    "national_code": "0024986021",
    "phone": "09177585872",
    "first_name": "مهدیه",
    "last_name": "مقیسهء",
    "email": "m.moghiseh@jabama.com"
  },
  {
    "personnel_number": 991756,
    "full_name": "زهره سادات کاشی",
    "department": "operation",
    "cooperation_start_date": "2024/02/01",
    "birthdate": "2000/04/24",
    "national_code": "0023147271",
    "phone": "09372217938",
    "first_name": "زهره",
    "last_name": "سادات کاشی",
    "email": "z.kashi@jabama.com"
  },
  {
    "personnel_number": 991520,
    "full_name": "محمدمهدی شیرازی زند",
    "department": "jaran",
    "cooperation_start_date": "2019/09/15",
    "birthdate": "1984/08/23",
    "national_code": "0074573462",
    "phone": "09124090089",
    "first_name": "محمدمهدی",
    "last_name": "شیرازی زند",
    "email": "mm.shirazi@alibaba.ir"
  },
  {
    "personnel_number": 991524,
    "full_name": "علیرضا احمدیان افشار",
    "department": "tech",
    "cooperation_start_date": "2023/08/23",
    "birthdate": "1994/03/04",
    "national_code": 3980205053,
    "phone": "09367198181",
    "first_name": "علیرضا",
    "last_name": "احمدیان افشار",
    "email": "al.afshar@jabama.com"
  },
  {
    "personnel_number": 991527,
    "full_name": "سید محمد عرفان طباطبایی",
    "department": "operation",
    "cooperation_start_date": "2023/08/05",
    "birthdate": "2001/11/19",
    "national_code": "0024932914",
    "phone": "09129558493",
    "first_name": "سید",
    "last_name": "محمد عرفان طباطبایی",
    "email": "e.tabatabaee@jabama.com"
  },
  {
    "personnel_number": 991529,
    "full_name": "غزاله قاضی زاده",
    "department": "operation",
    "cooperation_start_date": "2023/08/05",
    "birthdate": "1997/08/09",
    "national_code": "0020341563",
    "phone": "09302933977",
    "first_name": "غزاله",
    "last_name": "قاضی زاده",
    "email": "g.ghazizade@jabama.com"
  },
  {
    "personnel_number": 991999,
    "full_name": "سید مرتضی حافظی",
    "department": "human resources",
    "cooperation_start_date": "2024/09/22",
    "birthdate": "1989/03/28",
    "national_code": "0480009694",
    "phone": "09197739389",
    "first_name": "سید",
    "last_name": "مرتضی حافظی",
    "email": "s.hafezi@jabama.com"
  },
  {
    "personnel_number": 991550,
    "full_name": "بهزاد احسانی",
    "department": "tech",
    "cooperation_start_date": "2023/10/23",
    "birthdate": "1994/02/06",
    "national_code": 1361365978,
    "phone": "09366254431",
    "first_name": "بهزاد",
    "last_name": "احسانی",
    "email": "b.ehsani@jabama.com"
  },
  {
    "personnel_number": 991968,
    "full_name": "ارغوان سمر",
    "department": "marketing",
    "cooperation_start_date": "2024/08/03",
    "birthdate": "1995/01/03",
    "national_code": "0440447844",
    "phone": "09120908564",
    "first_name": "ارغوان",
    "last_name": "سمر",
    "email": "a.samar@jabama.com"
  },
  {
    "personnel_number": 1001023,
    "full_name": "علی کشاورز با حقیقت",
    "department": "tech",
    "cooperation_start_date": "2024/11/23",
    "birthdate": "1996/04/04",
    "national_code": "0018914462",
    "phone": "09126476040",
    "first_name": "علی",
    "last_name": "کشاورز با حقیقت",
    "email": "al.keshavarz@jabama.com"
  },
  {
    "personnel_number": 991545,
    "full_name": "مهدی فرهادی کلین",
    "department": "finance",
    "cooperation_start_date": "2023/10/17",
    "birthdate": "1998/10/26",
    "national_code": "0480906998",
    "phone": "09190232090",
    "first_name": "مهدی",
    "last_name": "فرهادی کلین",
    "email": "mah.farhadi@jabama.com"
  },
  {
    "personnel_number": 991534,
    "full_name": "علیرضا آویژگان",
    "department": "marketing",
    "cooperation_start_date": "2023/09/09",
    "birthdate": "1995/04/06",
    "national_code": "0017950252",
    "phone": "09126358967",
    "first_name": "علیرضا",
    "last_name": "آویژگان",
    "email": "a.avizhgan@jabama.com"
  },
  {
    "personnel_number": 991768,
    "full_name": "عرفان مداحی",
    "department": "operation",
    "cooperation_start_date": "2024/02/05",
    "birthdate": "1998/02/06",
    "national_code": "0020825552",
    "phone": "09337788507",
    "first_name": "عرفان",
    "last_name": "مداحی",
    "email": "e.madahi@jabama.com"
  },
  {
    "personnel_number": 991551,
    "full_name": "رامینا نقیون",
    "department": "marketing",
    "cooperation_start_date": "2023/11/22",
    "birthdate": "1986/06/30",
    "national_code": "0453648622",
    "phone": "09195326953",
    "first_name": "رامینا",
    "last_name": "نقیون",
    "email": "r.naghioun@jabama.com"
  },
  {
    "personnel_number": 990401,
    "full_name": "فرهاد البهشتی",
    "department": "marketing",
    "cooperation_start_date": "2021/05/22",
    "birthdate": "1992/04/28",
    "national_code": "0014526867",
    "phone": "09126274363",
    "first_name": "فرهاد",
    "last_name": "البهشتی",
    "email": "f.beheshti@jabama.com"
  },
  {
    "personnel_number": 991665,
    "full_name": "فاطمه خوشدونی فراهانی",
    "department": "human resources",
    "cooperation_start_date": "2023/11/22",
    "birthdate": "1983/06/13",
    "national_code": "0073507989",
    "phone": "09122858561",
    "first_name": "فاطمه",
    "last_name": "خوشدونی فراهانی",
    "email": "m.farahany@jabama.com"
  },
  {
    "personnel_number": 991671,
    "full_name": "سینا  شریف زاده",
    "department": "operation",
    "cooperation_start_date": "2023/11/18",
    "birthdate": "1999/03/06",
    "national_code": 2880329264,
    "phone": "09033233801",
    "first_name": "سینا",
    "last_name": " شریف زاده",
    "email": "s.sharifzadeh@jabama.com"
  },
  {
    "personnel_number": 991675,
    "full_name": "علیرضا پورمند",
    "department": "operation",
    "cooperation_start_date": "2023/11/19",
    "birthdate": "1997/06/29",
    "national_code": "0020240287",
    "phone": "09197230116",
    "first_name": "علیرضا",
    "last_name": "پورمند",
    "email": "a.pourmand@jabama.com"
  },
  {
    "personnel_number": 991677,
    "full_name": "نیلوفر رنجبر کاریزکی",
    "department": "operation",
    "cooperation_start_date": "2023/11/27",
    "birthdate": "1999/10/26",
    "national_code": "0022601988",
    "phone": "09382019083",
    "first_name": "نیلوفر",
    "last_name": "رنجبر کاریزکی",
    "email": "n.ranjbar@jabama.com"
  },

  {
    "personnel_number": 991687,
    "full_name": "ریحانه روشن قلب",
    "department": "marketing",
    "cooperation_start_date": "2024/01/13",
    "birthdate": "1993/07/30",
    "national_code": "0016123204",
    "phone": "09362756222",
    "first_name": "ریحانه",
    "last_name": "روشن قلب",
    "email": "r.roshanghalb@jabama.com"
  },
  {
    "personnel_number": 990239,
    "full_name": "مهدی زارعی",
    "department": "tech",
    "cooperation_start_date": "2020/09/01",
    "birthdate": "2000/02/07",
    "national_code": 3861132486,
    "phone": "09306095065",
    "first_name": "مهدی",
    "last_name": "زارعی",
    "email": "m.zareei@jabama.com"
  },
  {
    "personnel_number": 990459,
    "full_name": "پویا زاهدی",
    "department": "operation",
    "cooperation_start_date": "2021/07/03",
    "birthdate": "1996/01/04",
    "national_code": "0018682995",
    "phone": "09361488174",
    "first_name": "پویا",
    "last_name": "زاهدی",
    "email": "p.zahedi@jabama.com"
  },
  {
    "personnel_number": 991694,
    "full_name": "پانیذ طهرانیان شهباز",
    "department": "operation",
    "cooperation_start_date": "2024/01/21",
    "birthdate": "1997/09/07",
    "national_code": "0020454031",
    "phone": "09120058587",
    "first_name": "پانیذ",
    "last_name": "طهرانیان شهباز",
    "email": "p.tehranian@jabama.com"
  },
  {
    "personnel_number": 991695,
    "full_name": "فریبا  قنبری کسلانی",
    "department": "tech",
    "cooperation_start_date": "2024/02/20",
    "birthdate": "1992/03/12",
    "national_code": 4900203361,
    "phone": "09217155383",
    "first_name": "فریبا",
    "last_name": " قنبری کسلانی",
    "email": "fa.ghanbari@jabama.com"
  },
  {
    "personnel_number": 991696,
    "full_name": "فاطمه حاجی علی اکبر",
    "department": "operation",
    "cooperation_start_date": "2024/02/20",
    "birthdate": "1998/10/11",
    "national_code": "0021546363",
    "phone": "09126125698",
    "first_name": "فاطمه",
    "last_name": "حاجی علی اکبر",
    "email": "f.haji@jabama.com"
  },
  {
    "personnel_number": 991752,
    "full_name": "امیرعباس بهروزیان",
    "department": "operation",
    "cooperation_start_date": "2024/01/14",
    "birthdate": "1996/09/20",
    "national_code": 1742456898,
    "phone": "09190971140",
    "first_name": "امیرعباس",
    "last_name": "بهروزیان",
    "email": "a.behrooziyan@jabama.com"
  },
  {
    "personnel_number": 991684,
    "full_name": "محمد ترقی",
    "department": "human resources",
    "cooperation_start_date": "2023/12/22",
    "birthdate": "1994/05/04",
    "national_code": "0016942159",
    "phone": "09124219757",
    "first_name": "محمد",
    "last_name": "ترقی",
    "email": "m.taraghi@jabama.com"
  },
  {
    "personnel_number": 991540,
    "full_name": "فرناز ملک زاده بافقی",
    "department": "operation",
    "cooperation_start_date": "2023/09/17",
    "birthdate": "1999/02/07",
    "national_code": 4420799749,
    "phone": "09377607222",
    "first_name": "فرناز",
    "last_name": "ملک زاده بافقی",
    "email": "f.malekzade@jabama.com"
  },
  {
    "personnel_number": 991798,
    "full_name": "شقایق قلی زاده",
    "department": "operation",
    "cooperation_start_date": "2024/02/04",
    "birthdate": "2003/10/31",
    "national_code": "0150488718",
    "phone": "09057188730",
    "first_name": "شقایق",
    "last_name": "قلی زاده",
    "email": "s.gholizadeh@jabama.com"
  },
  {
    "personnel_number": 991800,
    "full_name": "محمدرضا قاسمی",
    "department": "operation",
    "cooperation_start_date": "2024/02/04",
    "birthdate": "2003/06/26",
    "national_code": 2283637341,
    "phone": "09052137599",
    "first_name": "محمدرضا",
    "last_name": "قاسمی",
    "email": "mr.ghasemi@jabama.com"
  },
  {
    "personnel_number": 991802,
    "full_name": "مهدی سیرانی",
    "department": "operation",
    "cooperation_start_date": "2024/02/04",
    "birthdate": "2001/11/05",
    "national_code": "0024681555",
    "phone": "09389428139",
    "first_name": "مهدی",
    "last_name": "سیرانی",
    "email": "m.sirani@jabama.com"
  },
  {
    "personnel_number": 991820,
    "full_name": "نويد جعفرپناهي",
    "department": "operation",
    "cooperation_start_date": "2024/02/20",
    "birthdate": "1992/10/31",
    "national_code": 4120326012,
    "phone": "09365326803",
    "first_name": "نويد",
    "last_name": "جعفرپناهي",
    "email": "n.jafarpanahi@jabama.com"
  },
  {
    "personnel_number": 991823,
    "full_name": "سعید شیرازی",
    "department": "tech",
    "cooperation_start_date": "2024/03/20",
    "birthdate": "1993/07/16",
    "national_code": "0016071999",
    "phone": "09355947263",
    "first_name": "سعید",
    "last_name": "شیرازی",
    "email": "sa.shirazi@jabama.com"
  },
  {
    "personnel_number": 1991933,
    "full_name": "علیرضا شیخ",
    "department": "jaran",
    "cooperation_start_date": "2024/04/03",
    "birthdate": "1981/02/09",
    "national_code": 1289091943,
    "phone": "09122495649",
    "first_name": "علیرضا",
    "last_name": "شیخ",
    "email": "a.sheykh@jarantravel.com"
  },
  {
    "personnel_number": 991313,
    "full_name": "دانا  امینی راد",
    "department": "tech",
    "cooperation_start_date": "2023/04/21",
    "birthdate": "2000/04/06",
    "national_code": 1273168011,
    "phone": "09919926630",
    "first_name": "دانا",
    "last_name": " امینی راد",
    "email": "d.aminirad@jabama.com"
  },
  {
    "personnel_number": 991828,
    "full_name": "مهیار  بختیاری",
    "department": "operation",
    "cooperation_start_date": "2024/02/18",
    "birthdate": "2000/07/30",
    "national_code": "0023358531",
    "phone": "09198406627",
    "first_name": "مهیار",
    "last_name": "بختیاری",
    "email": "m.bakhtiari@jabama.com"
  },
  {
    "personnel_number": 991829,
    "full_name": "شقایق نصری",
    "department": "operation",
    "cooperation_start_date": "2024/02/18",
    "birthdate": "2001/12/05",
    "national_code": 3720961036,
    "phone": "09196771297",
    "first_name": "شقایق",
    "last_name": "نصری",
    "email": "s.nasri@jabama.com"
  },
  {
    "personnel_number": 1001022,
    "full_name": "احمدرضا محسنی",
    "department": "finance",
    "cooperation_start_date": "2024/11/16",
    "birthdate": "2001/04/08",
    "national_code": 1201640966,
    "phone": "09226589740",
    "first_name": "احمدرضا",
    "last_name": "محسنی",
    "email": "a.mohseni@jabama.com"
  },
  {
    "personnel_number": 991833,
    "full_name": "حسین بهزادی موحد",
    "department": "operation",
    "cooperation_start_date": "2024/02/21",
    "birthdate": "2003/10/15",
    "national_code": "0150479735",
    "phone": "09202269875",
    "first_name": "حسین",
    "last_name": "بهزادی موحد",
    "email": "h.behzadimovahhed@jabama.com"
  },
  {
    "personnel_number": 991840,
    "full_name": "حانیه زارعی نمین",
    "department": "product",
    "cooperation_start_date": "2024/03/20",
    "birthdate": "1996/06/13",
    "national_code": "0019155875",
    "phone": "09190849177",
    "first_name": "حانیه",
    "last_name": "زارعی نمین",
    "email": "ha.zarei@jabama.com"
  },
  {
    "personnel_number": 991846,
    "full_name": "محمدحسین فروهش طهرانی",
    "department": "tech",
    "cooperation_start_date": "2024/04/15",
    "birthdate": "1996/12/12",
    "national_code": "0019655312",
    "phone": "09919002015",
    "first_name": "محمدحسین",
    "last_name": "فروهش طهرانی",
    "email": "m.forohesh@jabama.com"
  },
  {
    "personnel_number": 991292,
    "full_name": "محمدرضا ملکلو",
    "department": "finance",
    "cooperation_start_date": "2023/02/28",
    "birthdate": "1992/02/11",
    "national_code": "0310659833",
    "phone": "09124626104",
    "first_name": "محمدرضا",
    "last_name": "ملکلو",
    "email": "m.malekloo@jabama.com"
  },
  {
    "personnel_number": 991943,
    "full_name": "علیرضا  بابازاده کمانگر",
    "department": "tech",
    "cooperation_start_date": "2024/06/08",
    "birthdate": "2000/01/06",
    "national_code": 2050964161,
    "phone": "09056506540",
    "first_name": "علیرضا",
    "last_name": " بابازاده کمانگر",
    "email": "ar.babazadeh@jabama.com"
  },
  {
    "personnel_number": 991395,
    "full_name": "سیدامیر سیدحسن طهرانی",
    "department": "operation",
    "cooperation_start_date": "2023/05/20",
    "birthdate": "1993/01/06",
    "national_code": "0015405885",
    "phone": "09354093777",
    "first_name": "سیدامیر",
    "last_name": "سیدحسن طهرانی",
    "email": "a.tehrani@jabama.com"
  },
  {
    "personnel_number": 991407,
    "full_name": "ریحانه امینی",
    "department": "operation",
    "cooperation_start_date": "2023/05/25",
    "birthdate": "1999/01/07",
    "national_code": "0021768201",
    "phone": "09214408682",
    "first_name": "ریحانه",
    "last_name": "امینی",
    "email": "r.amini@jabama.com"
  },
  {
    "personnel_number": 991941,
    "full_name": "مهدی اثباتی",
    "department": "tech",
    "cooperation_start_date": "2024/05/07",
    "birthdate": "2001/08/12",
    "national_code": "0024403962",
    "phone": "09383446933",
    "first_name": "مهدی",
    "last_name": "اثباتی",
    "email": "m.esbati@jabama.com"
  },
  {
    "personnel_number": 991691,
    "full_name": "فاطمه بیات",
    "department": "operation",
    "cooperation_start_date": "2023/12/31",
    "birthdate": "1999/01/08",
    "national_code": "0311895018",
    "phone": "09384094941",
    "first_name": "فاطمه",
    "last_name": "بیات",
    "email": "f.bayat@jabama.com"
  },
  {
    "personnel_number": 1001007,
    "full_name": "فهیمه نجفی پور  نوکنده",
    "department": "finance",
    "cooperation_start_date": "2024/10/01",
    "birthdate": "1986/02/11",
    "national_code": "0083764844",
    "phone": "09122885721",
    "first_name": "فهیمه",
    "last_name": "نجفی پور  نوکنده",
    "email": "f.najafipour@jabama.com"
  },
  {
    "personnel_number": 991541,
    "full_name": "عسل ناصری نیا",
    "department": "operation",
    "cooperation_start_date": "2023/09/17",
    "birthdate": "2003/01/09",
    "national_code": 1743852517,
    "phone": "09023754481",
    "first_name": "عسل",
    "last_name": "ناصری نیا",
    "email": "as.naseri@jabama.com"
  },
  {
    "personnel_number": 990460,
    "full_name": "مهرشاد ابراهیمی زیبا",
    "department": "operation",
    "cooperation_start_date": "2021/07/03",
    "birthdate": "1996/02/12",
    "national_code": "0018804330",
    "phone": "09129373588",
    "first_name": "مهرشاد",
    "last_name": "ابراهیمی زیبا",
    "email": "m.ebrahimi@jabama.com"
  },
  {
    "personnel_number": 991959,
    "full_name": "احسان بابازاده رضایی",
    "department": "operation",
    "cooperation_start_date": "2024/05/18",
    "birthdate": "1999/03/08",
    "national_code": "0021922403",
    "phone": "09304720662",
    "first_name": "احسان",
    "last_name": "بابازاده رضایی",
    "email": "e.babazadeh@jabama.com"
  },
  {
    "personnel_number": 991964,
    "full_name": "دنیا عباسپور",
    "department": "operation",
    "cooperation_start_date": "2024/05/21",
    "birthdate": "2000/03/07",
    "national_code": "0022961410",
    "phone": "09925361609",
    "first_name": "دنیا",
    "last_name": "عباسپور",
    "email": "d.abbaspour@jabama.com"
  },
  {
    "personnel_number": 991966,
    "full_name": "احسان موفق",
    "department": "tech",
    "cooperation_start_date": "2024/06/21",
    "birthdate": "2001/07/08",
    "national_code": "0024273813",
    "phone": "09016939454",
    "first_name": "احسان",
    "last_name": "موفق",
    "email": "e.movafagh@jabama.com"
  },
  {
    "personnel_number": 991967,
    "full_name": "علی سبحانی",
    "department": "jaran",
    "cooperation_start_date": "2024/06/21",
    "birthdate": "1992/11/07",
    "national_code": "0015501124",
    "phone": "09191009283",
    "first_name": "علی",
    "last_name": "سبحانی",
    "email": "al.sobhani@jarantravel.com"
  },
  {
    "personnel_number": 991970,
    "full_name": "حمید شیرمحمدکریمی",
    "department": "tech",
    "cooperation_start_date": "2024/07/06",
    "birthdate": "1991/07/22",
    "national_code": "0013665391",
    "phone": "09124027849",
    "first_name": "حمید",
    "last_name": "شیرمحمدکریمی",
    "email": "ham.karimi@jabama.com"
  },
  {
    "personnel_number": 991971,
    "full_name": "سیدمجتبی سجادی نیا",
    "department": "tech",
    "cooperation_start_date": "2024/07/22",
    "birthdate": "1987/11/28",
    "national_code": "0083057625",
    "phone": "09195059755",
    "first_name": "سیدمجتبی",
    "last_name": "سجادی نیا",
    "email": "m.sajadinia@jabama.com"
  },
  {
    "personnel_number": 991546,
    "full_name": "نرگس یوسفیان",
    "department": "operation",
    "cooperation_start_date": "2023/10/07",
    "birthdate": "2001/04/09",
    "national_code": 24131741,
    "phone": "09912015462",
    "first_name": "نرگس",
    "last_name": "یوسفیان",
    "email": "n.yousefian@jabama.com"
  },
  {
    "personnel_number": 991980,
    "full_name": "عدنان اسعدی",
    "department": "human resources",
    "cooperation_start_date": "2024/07/22",
    "birthdate": "1987/10/25",
    "national_code": "0079771130",
    "phone": "09121839532",
    "first_name": "عدنان",
    "last_name": "اسعدی",
    "email": "ad.asadi@jabama.com"
  },
  {
    "personnel_number": 991981,
    "full_name": "سلمان  سیفی پیرالقر",
    "department": "human resources",
    "cooperation_start_date": "2024/07/22",
    "birthdate": "1972/09/23",
    "national_code": 1465298908,
    "phone": "09105690493",
    "first_name": "سلمان",
    "last_name": " سیفی پیرالقر",
    "email": "sa.seyfi@jabama.com"
  },
  {
    "personnel_number": 991983,
    "full_name": "سیده تمنا منصوری",
    "department": "marketing",
    "cooperation_start_date": "2024/08/05",
    "birthdate": "1989/09/27",
    "national_code": 2270009665,
    "phone": "09113957661",
    "first_name": "سیده",
    "last_name": "تمنا منصوری",
    "email": "t.mansouri@jabama.com"
  },
  {
    "personnel_number": 991984,
    "full_name": "سحر بختیاری",
    "department": "product",
    "cooperation_start_date": "2024/08/22",
    "birthdate": "1992/09/09",
    "national_code": "0016346807",
    "phone": "09127239624",
    "first_name": "سحر",
    "last_name": "بختیاری",
    "email": "s.bakhtiyari@jabama.com"
  },
  {
    "personnel_number": 991986,
    "full_name": "محمدعلی بیجار گروس",
    "department": "finance",
    "cooperation_start_date": "2024/07/30",
    "birthdate": "1999/02/24",
    "national_code": "0021902569",
    "phone": "09376161350",
    "first_name": "محمدعلی",
    "last_name": "بیجار گروس",
    "email": "m.garous@jabama.com"
  },
  {
    "personnel_number": 991987,
    "full_name": "عین اله عباسی",
    "department": "human resources",
    "cooperation_start_date": "2024/08/05",
    "birthdate": "1983/11/02",
    "national_code": "0559537832",
    "phone": "09121481992",
    "first_name": "عین",
    "last_name": "اله عباسی",
    "email": "ey.abbasi@jabama.com"
  },
  {
    "personnel_number": 95305,
    "full_name": "لیلا سلطانی",
    "department": "human resources",
    "cooperation_start_date": "2017/04/29",
    "birthdate": "1991/01/18",
    "national_code": "0012934844",
    "phone": "09353366724",
    "first_name": "لیلا",
    "last_name": "سلطانی",
    "email": "l.soltani@jabama.com"
  },
  {
    "personnel_number": 991989,
    "full_name": "گلناز سلطانی",
    "department": "operation",
    "cooperation_start_date": "2024/08/03",
    "birthdate": "1992/06/30",
    "national_code": "0310729505",
    "phone": "09361955813",
    "first_name": "گلناز",
    "last_name": "سلطانی",
    "email": "g.soltani@jabama.com"
  },
  {
    "personnel_number": 991990,
    "full_name": "هانیه تاجیک",
    "department": "operation",
    "cooperation_start_date": "2024/08/05",
    "birthdate": "2002/12/16",
    "national_code": "0110185250",
    "phone": "09192224262",
    "first_name": "هانیه",
    "last_name": "تاجیک",
    "email": "h.tajik@jabama.com"
  },
  {
    "personnel_number": 991690,
    "full_name": "محمد مهدی برمکی",
    "department": "operation",
    "cooperation_start_date": "2023/12/31",
    "birthdate": "2003/02/16",
    "national_code": "0025371657",
    "phone": "09035677633",
    "first_name": "محمد",
    "last_name": "مهدی برمکی",
    "email": "mo.barmaki@jabama.com"
  },
  {
    "personnel_number": 991430,
    "full_name": "محدثه نجفی",
    "department": "marketing",
    "cooperation_start_date": "2023/07/08",
    "birthdate": "1995/01/18",
    "national_code": "0017732530",
    "phone": "09903966607",
    "first_name": "محدثه",
    "last_name": "نجفی",
    "email": "mo.najafi@jabama.com"
  },
  {
    "personnel_number": 991995,
    "full_name": "نازنین مطلبی",
    "department": "tech",
    "cooperation_start_date": "2024/08/22",
    "birthdate": "1989/08/20",
    "national_code": "0010799842",
    "phone": "09124136132",
    "first_name": "نازنین",
    "last_name": "مطلبی",
    "email": "n.motalebi@jabama.com"
  },
  {
    "personnel_number": 991996,
    "full_name": "امیر محسن امینی",
    "department": "marketing",
    "cooperation_start_date": "2024/09/05",
    "birthdate": "1995/03/14",
    "national_code": 2710243903,
    "phone": "09339684159",
    "first_name": "امیر محسن",
    "last_name": "امینی",
    "email": "a.amini@jabama.com"
  },
  {
    "personnel_number": 991997,
    "full_name": "شایسته عابدینی",
    "department": "human resources",
    "cooperation_start_date": "2024/09/22",
    "birthdate": "1997/04/10",
    "national_code": "0019966814",
    "phone": "09123348785",
    "first_name": "شایسته",
    "last_name": "عابدینی",
    "email": "sh.abedini@jabama.com"
  },
  {
    "personnel_number": 991998,
    "full_name": "فاطمه معیری راد",
    "department": "tech",
    "cooperation_start_date": "2024/09/14",
    "birthdate": "2002/05/24",
    "national_code": "0024954705",
    "phone": "09106875590",
    "first_name": "فاطمه",
    "last_name": "معیری راد",
    "email": "r.moayerirad@jabama.com"
  },
  {
    "personnel_number": 1001048,
    "full_name": "زهرا عباسی",
    "department": "operation",
    "cooperation_start_date": "2025/01/25",
    "birthdate": "2002/04/12",
    "national_code": "0312476892",
    "phone": "09926210226",
    "first_name": "زهرا",
    "last_name": "عباسی",
    "email": "z.abbasi@jabama.com"
  },
  {
    "personnel_number": 1001028,
    "full_name": "محمدجواد قادری",
    "department": "product",
    "cooperation_start_date": "2024/12/21",
    "birthdate": "1987/05/07",
    "national_code": 2300230331,
    "phone": "09122564990",
    "first_name": "محمدجواد",
    "last_name": "قادری",
    "email": "m.ghaderi@jabama.com"
  },
  {
    "personnel_number": 1001002,
    "full_name": "دانیال معایشی",
    "department": "tech",
    "cooperation_start_date": "2024/08/31",
    "birthdate": "1998/07/16",
    "national_code": "0021282161",
    "phone": "09120186297",
    "first_name": "دانیال",
    "last_name": "معایشی",
    "email": "d.maayeshi@jabama.com"
  },
  {
    "personnel_number": 1001003,
    "full_name": "مرضیه حقیقی",
    "department": "marketing",
    "cooperation_start_date": "2024/09/22",
    "birthdate": "1995/12/06",
    "national_code": 1272063143,
    "phone": "09371211107",
    "first_name": "مرضیه",
    "last_name": "حقیقی",
    "email": "m.haghighi@jabama.com"
  },

  {
    "personnel_number": 1001014,
    "full_name": "قاسم کاظمی",
    "department": "operation",
    "cooperation_start_date": "2024/10/31",
    "birthdate": "1986/01/18",
    "national_code": "0077765524",
    "phone": "09127083664",
    "first_name": "قاسم",
    "last_name": "کاظمی",
    "email": "gh.kazemi@jabama.com"
  },
  {
    "personnel_number": 991767,
    "full_name": "سینا علیپور کلده",
    "department": "operation",
    "cooperation_start_date": "2024/01/28",
    "birthdate": "1994/05/08",
    "national_code": "0016797116",
    "phone": "09195093065",
    "first_name": "سینا",
    "last_name": "علیپور کلده",
    "email": "s.alipour@jabama.com"
  },
  {
    "personnel_number": 991824,
    "full_name": "نیوشا  شکاری",
    "department": "human resources",
    "cooperation_start_date": "2024/02/18",
    "birthdate": "1999/02/17",
    "national_code": "0440781043",
    "phone": "09194097610",
    "first_name": "نیوشا",
    "last_name": " شکاری",
    "email": "n.shekari@jabama.com"
  },
  {
    "personnel_number": 1001010,
    "full_name": "آرمین مربی",
    "department": "operation",
    "cooperation_start_date": "2024/09/24",
    "birthdate": "1995/08/29",
    "national_code": "0018450806",
    "phone": "09226791269",
    "first_name": "آرمین",
    "last_name": "مربی",
    "email": "a.morabi@jabama.com"
  },
  {
    "personnel_number": 1001011,
    "full_name": "پارسا محتشم زاده",
    "department": "operation",
    "cooperation_start_date": "2024/09/24",
    "birthdate": "2000/11/26",
    "national_code": "0023750448",
    "phone": 9012516705,
    "first_name": "پارسا",
    "last_name": "محتشم زاده",
    "email": "p.mohtashamzadeh@jabama.com"
  },
  {
    "personnel_number": 1001001,
    "full_name": "مهدی پوربرات",
    "department": "finance",
    "cooperation_start_date": "2024/09/22",
    "birthdate": "1986/05/08",
    "national_code": "0079356850",
    "phone": "09120321228",
    "first_name": "مهدی",
    "last_name": "پوربرات",
    "email": "m.pourbarat@jabama.com"
  },
  {
    "personnel_number": 991422,
    "full_name": "صابر اولیایی",
    "department": "operation",
    "cooperation_start_date": "2023/06/22",
    "birthdate": "1996/01/19",
    "national_code": "0018766633",
    "phone": "09109785190",
    "first_name": "صابر",
    "last_name": "اولیایی",
    "email": "s.oliaee@jabama.com"
  },
  {
    "personnel_number": 1001015,
    "full_name": "ملیکا یگانه",
    "department": "marketing",
    "cooperation_start_date": "2024/09/22",
    "birthdate": "1999/03/01",
    "national_code": "0022054359",
    "phone": "09021727207",
    "first_name": "ملیکا",
    "last_name": "یگانه",
    "email": "m.yeganeh@jabama.com"
  },
  {
    "personnel_number": 1001019,
    "full_name": "آیسودا  ابوالحسن بیگی گله زن",
    "department": "tech",
    "cooperation_start_date": "2024/11/21",
    "birthdate": "1998/09/11",
    "national_code": 6790076794,
    "phone": "09906653136",
    "first_name": "آیسودا",
    "last_name": " ابوالحسن بیگی گله زن",
    "email": "a.beigi@jabama.com"
  },
  {
    "personnel_number": 1001018,
    "full_name": "جلیل بهرامی",
    "department": "finance",
    "cooperation_start_date": "2024/11/02",
    "birthdate": "1990/11/11",
    "national_code": 4020079293,
    "phone": "09126631424",
    "first_name": "جلیل",
    "last_name": "بهرامی",
    "email": "j.bahrami@jabama.com"
  },
  {
    "personnel_number": 1001016,
    "full_name": "زینب حمیدی بنام",
    "department": "legal",
    "cooperation_start_date": "2024/11/21",
    "birthdate": "1988/09/05",
    "national_code": "0083688811",
    "phone": "09124403175",
    "first_name": "زینب",
    "last_name": "حمیدی بنام",
    "email": "z.hamidi@jabama.com"
  },
  {
    "personnel_number": 1001039,
    "full_name": "محمدحسین فضلعلی",
    "department": "product",
    "cooperation_start_date": "2024/12/28",
    "birthdate": "1994/05/10",
    "national_code": "0016884876",
    "phone": "09125283754",
    "first_name": "محمدحسین",
    "last_name": "فضلعلی",
    "email": "m.fazlali@jabama.com"
  },
  {
    "personnel_number": 991542,
    "full_name": "الهام خاطری",
    "department": "operation",
    "cooperation_start_date": "2023/09/23",
    "birthdate": "1993/04/19",
    "national_code": "0015685861",
    "phone": "09356318994",
    "first_name": "الهام",
    "last_name": "خاطری",
    "email": "e.khateri@jabama.com"
  },
  {
    "personnel_number": 1001033,
    "full_name": "سهیل سمیعی پاقلعه",
    "department": "marketing",
    "cooperation_start_date": "2024/12/21",
    "birthdate": "1994/09/13",
    "national_code": 4860168331,
    "phone": "09217340178",
    "first_name": "سهیل",
    "last_name": "سمیعی پاقلعه",
    "email": "so.samiei@jabama.com"
  },
  {
    "personnel_number": 991558,
    "full_name": "سید سهیل مقیمی",
    "department": "operation",
    "cooperation_start_date": "2024/11/23",
    "birthdate": "1999/06/02",
    "national_code": "0022142169",
    "phone": "09190242455",
    "first_name": "سید",
    "last_name": "سهیل مقیمی",
    "email": "so.moghimi@jabama.com"
  },
  {
    "personnel_number": 991991,
    "full_name": "رضا باقري صفت بلسبنهء",
    "department": "operation",
    "cooperation_start_date": "2024/08/05",
    "birthdate": "1997/02/18",
    "national_code": "0019850077",
    "phone": "09212208505",
    "first_name": "رضا",
    "last_name": "باقري صفت بلسبنهء",
    "email": "r.bagherisefat@jabama.com"
  },
  {
    "personnel_number": 1001034,
    "full_name": "شروین روح افزا",
    "department": "operation",
    "cooperation_start_date": "2024/12/09",
    "birthdate": "2000/11/22",
    "national_code": "0440906547",
    "phone": "09378720287",
    "first_name": "شروین",
    "last_name": "روح افزا",
    "email": "s.rouhafza@jabama.com"
  },
  {
    "personnel_number": 1001026,
    "full_name": "آیدین بهرمان",
    "department": "product",
    "cooperation_start_date": "2024/12/21",
    "birthdate": "1991/04/19",
    "national_code": "0013344978",
    "phone": "09120184864",
    "first_name": "آیدین",
    "last_name": "بهرمان",
    "email": "a.bahreman@jabama.com"
  },
  {
    "personnel_number": 97684,
    "full_name": "ریحانه صفری",
    "department": "tech",
    "cooperation_start_date": "2020/01/05",
    "birthdate": "1995/05/11",
    "national_code": "0018336541",
    "phone": "09912012092",
    "first_name": "ریحانه",
    "last_name": "صفری",
    "email": "as.safari@jabama.com"
  },
  {
    "personnel_number": 1001027,
    "full_name": "محدثه  نعمتی اقدم",
    "department": "operation",
    "cooperation_start_date": "2024/12/07",
    "birthdate": "1998/09/22",
    "national_code": "0021472440",
    "phone": "09120254164",
    "first_name": "محدثه",
    "last_name": " نعمتی اقدم",
    "email": "mo.nemati@jabama.com"
  },
  {
    "personnel_number": 1001032,
    "full_name": "امیرمحمد نادری",
    "department": "tech",
    "cooperation_start_date": "2024/12/21",
    "birthdate": "1993/05/15",
    "national_code": "0015787303",
    "phone": "09378855146",
    "first_name": "امیرمحمد",
    "last_name": "نادری",
    "email": "am.naderi@jabama.com"
  },
  {
    "personnel_number": 991439,
    "full_name": "فاطمه پاسبان",
    "department": "finance",
    "cooperation_start_date": "2023/07/10",
    "birthdate": "1998/05/19",
    "national_code": "0924420510",
    "phone": "09150758803",
    "first_name": "فاطمه",
    "last_name": "پاسبان",
    "email": "f.paseban@jabama.com"
  },
  {
    "personnel_number": 990189,
    "full_name": "محمدسعید  سلطانی",
    "department": "strategy",
    "cooperation_start_date": "2024/12/07",
    "birthdate": "1997/07/16",
    "national_code": 2282408446,
    "phone": "09120615836",
    "first_name": "محمدسعید",
    "last_name": " سلطانی",
    "email": "sa.soltani@jabama.com"
  },
  {
    "personnel_number": 1001017,
    "full_name": "مهرداد ریاحی تملی",
    "department": "tech",
    "cooperation_start_date": "2024/11/21",
    "birthdate": "1999/09/20",
    "national_code": "0312024606",
    "phone": "09115013713",
    "first_name": "مهرداد",
    "last_name": "ریاحی تملی",
    "email": "ma.riyahi@jabama.com"
  },
  {
    "personnel_number": 1001040,
    "full_name": "مهرزاد گلی",
    "department": "product",
    "cooperation_start_date": "2025/01/04",
    "birthdate": "1995/12/04",
    "national_code": "0018927459",
    "phone": "09366160317",
    "first_name": "مهرزاد",
    "last_name": "گلی",
    "email": "m.goli@jabama.com"
  },
  {
    "personnel_number": 1001041,
    "full_name": "شادی غلمان",
    "department": "tech",
    "cooperation_start_date": "2025/01/11",
    "birthdate": "1994/01/19",
    "national_code": "0016469267",
    "phone": "09226523288",
    "first_name": "شادی",
    "last_name": "غلمان",
    "email": "s.ghelman@jabama.com"
  },
  {
    "personnel_number": 1001043,
    "full_name": "نوشین سیف اله ئی",
    "department": "operation",
    "cooperation_start_date": "2024/12/31",
    "birthdate": "1987/02/19",
    "national_code": "0453358764",
    "phone": "09125602954",
    "first_name": "نوشین",
    "last_name": "سیف اله ئی",
    "email": "n.seifollahi@jabama.com"
  },
  {
    "personnel_number": 991961,
    "full_name": "علی اصغر محمدی",
    "department": "operation",
    "cooperation_start_date": "2024/05/18",
    "birthdate": "1999/01/20",
    "national_code": "0021826609",
    "phone": "09398820898",
    "first_name": "علی اصغر",
    "last_name": "محمدی",
    "email": "ali.mohammadi@jabama.com"
  },
  {
    "personnel_number": 1001044,
    "full_name": "کیانا لیاقت",
    "department": "tech",
    "cooperation_start_date": "2025/01/25",
    "birthdate": "2000/08/08",
    "national_code": "0023471042",
    "phone": "09023380775",
    "first_name": "کیانا",
    "last_name": "لیاقت",
    "email": "k.liaghat@jabama.com"
  },
  {
    "personnel_number": 1001045,
    "full_name": "آیلار فلاحیان",
    "department": "operation",
    "cooperation_start_date": "2025/01/29",
    "birthdate": "1995/06/01",
    "national_code": "0018066925",
    "phone": "09377896756",
    "first_name": "آیلار",
    "last_name": "فلاحیان",
    "email": "ay.fallahian@jabama.com"
  },
  {
    "personnel_number": 1001046,
    "full_name": "علیرضا ملاصالحی",
    "department": "operation",
    "cooperation_start_date": "2025/02/01",
    "birthdate": "1993/05/22",
    "national_code": "0015935515",
    "phone": "09025206097",
    "first_name": "علیرضا",
    "last_name": "ملاصالحی",
    "email": "a.mollasalehi@jabama.com"
  },
  {
    "personnel_number": 1001047,
    "full_name": "مریم علی اکبر",
    "department": "operation",
    "cooperation_start_date": "2025/01/25",
    "birthdate": "2004/10/28",
    "national_code": "0150737033",
    "phone": "09375235758",
    "first_name": "مریم",
    "last_name": "علی اکبر",
    "email": "d.aliakbar@jabama.com"
  },
  {
    "personnel_number": 991825,
    "full_name": "شایان   رحیمی چگنی",
    "department": "operation",
    "cooperation_start_date": "2024/02/18",
    "birthdate": "2003/09/22",
    "national_code": 4061396110,
    "phone": "09017179617",
    "first_name": "شایان",
    "last_name": "  رحیمی چگنی",
    "email": "sh.rahimi@jabama.com"
  },

  {
    "personnel_number": 1001051,
    "full_name": "پارسا مهرعلیزاده",
    "department": "operation",
    "cooperation_start_date": "2025/01/25",
    "birthdate": "2003/09/28",
    "national_code": "0200096281",
    "phone": "09011372728",
    "first_name": "پارسا",
    "last_name": "مهرعلیزاده",
    "email": "p.mehralizadeh@jabama.com"
  },
  {
    "personnel_number": 1001052,
    "full_name": "فروغ داورزنی",
    "department": "finance",
    "cooperation_start_date": "2025/02/08",
    "birthdate": "1992/07/27",
    "national_code": "0014809982",
    "phone": "09122108869",
    "first_name": "فروغ",
    "last_name": "داورزنی",
    "email": "f.davarzani@jabama.com"
  },
  {
    "personnel_number": 1001055,
    "full_name": "مرضیه میرزکی",
    "department": "operation",
    "cooperation_start_date": "2025/04/05",
    "birthdate": "1991/08/28",
    "national_code": 4190181056,
    "phone": "09364113565",
    "first_name": "مرضیه",
    "last_name": "میرزکی",
    "email": "m.mirzaki@jabama.com"
  },
  {
    "personnel_number": 1001056,
    "full_name": "سعید گلی شیخ الاسلام",
    "department": "human resources",
    "cooperation_start_date": "2025/04/21",
    "birthdate": "1992/02/24",
    "national_code": 4900194212,
    "phone": "09367675148",
    "first_name": "سعید",
    "last_name": "گلی شیخ الاسلام",
    "email": "s.goli@jabama.com"
  },
  {
    "personnel_number": 1001057,
    "full_name": "محمدباقر خدائی",
    "department": "operation",
    "cooperation_start_date": "2025/05/06",
    "birthdate": "1997/07/14",
    "national_code": "0021931372",
    "phone": "09212631439",
    "first_name": "محمدباقر",
    "last_name": "خدائی",
    "email": "m.khodae@jabama.com"
  },
  {
    "personnel_number": 1001058,
    "full_name": "امیرحسین برادران",
    "department": "operation",
    "cooperation_start_date": "2025/05/07",
    "birthdate": "2003/10/22",
    "national_code": "0110339304",
    "phone": "09204041067",
    "first_name": "امیرحسین",
    "last_name": "برادران",
    "email": "a.baradaran@jabama.com"
  },
  {
    "personnel_number": 1001059,
    "full_name": "شیوا شفیعی",
    "department": "human resources",
    "cooperation_start_date": "2025/05/10",
    "birthdate": "1996/01/29",
    "national_code": 1180067568,
    "phone": "09120189278",
    "first_name": "شیوا",
    "last_name": "شفیعی",
    "email": "shi.shafiei@jabama.com"
  },
  {
    "personnel_number": 1001060,
    "full_name": "نجمه یزدانی",
    "department": "finance",
    "cooperation_start_date": "2025/05/31",
    "birthdate": "1999/07/17",
    "national_code": "0022288228",
    "phone": "09120372566",
    "first_name": "نجمه",
    "last_name": "یزدانی",
    "email": "n.yazdani@alibaba.ir"
  }
]
